collective.flexmailhost-1.0a1-py3.11-nspkg.pth
collective/flexmailhost/__init__.py
collective/flexmailhost/configure.zcml
collective/flexmailhost/interfaces.py
collective/flexmailhost/patches.py
collective/flexmailhost/permissions.zcml
collective/flexmailhost/setuphandlers.py
collective/flexmailhost/testing.py
collective/flexmailhost/browser/__init__.py
collective/flexmailhost/browser/configure.zcml
collective/flexmailhost/browser/overrides/.gitkeep
collective/flexmailhost/browser/static/.gitkeep
collective/flexmailhost/locales/README.rst
collective/flexmailhost/locales/__init__.py
collective/flexmailhost/locales/collective.flexmailhost.pot
collective/flexmailhost/locales/update.py
collective/flexmailhost/locales/update.sh
collective/flexmailhost/locales/en/LC_MESSAGES/collective.flexmailhost.po
collective/flexmailhost/profiles/default/browserlayer.xml
collective/flexmailhost/profiles/default/catalog.xml
collective/flexmailhost/profiles/default/metadata.xml
collective/flexmailhost/profiles/default/rolemap.xml
collective/flexmailhost/profiles/default/registry/main.xml
collective/flexmailhost/profiles/uninstall/browserlayer.xml
collective/flexmailhost/subscribers/__init__.py
collective/flexmailhost/subscribers/configure.zcml
collective/flexmailhost/subscribers/sync_mailhost_settings.py
collective/flexmailhost/tests/__init__.py
collective/flexmailhost/tests/test_robot.py
collective/flexmailhost/tests/test_setup.py
collective/flexmailhost/tests/test_subscriber_sync_mailhost_settings.py
collective/flexmailhost/tests/robot/test_example.robot
collective.flexmailhost-1.0a1.dist-info/LICENSE.GPL
collective.flexmailhost-1.0a1.dist-info/LICENSE.rst
collective.flexmailhost-1.0a1.dist-info/METADATA
collective.flexmailhost-1.0a1.dist-info/WHEEL
collective.flexmailhost-1.0a1.dist-info/entry_points.txt
collective.flexmailhost-1.0a1.dist-info/namespace_packages.txt
collective.flexmailhost-1.0a1.dist-info/top_level.txt
collective.flexmailhost-1.0a1.dist-info/RECORD
